<?xml version="1.0" encoding="utf-8" standalone="yes"?>
<T3locallang type="array">
  <meta type="array">
    <description>Language labels for backend of events (tx_t3events)</description>
    <type>database</type>
    <generator>LFEditor</generator>
  </meta>
  <data type="array">
    <languageKey index="default" type="array">
      <label index="flexforms_general.ascending">ascending</label>
      <label index="flexforms_general.backPage">Back Page</label>
      <label index="flexforms_general.cache.makeNonCacheable">Don't cache plugin contents</label>
      <label index="flexforms_general.conjunction">Conjunction</label>
      <label index="flexforms_general.conjunction.and">And</label>
      <label index="flexforms_general.conjunction.or">Or</label>
      <label index="flexforms_general.constraintBy">constraint by</label>
      <label index="flexforms_general.constraints">Constraints</label>
      <label index="flexforms_general.descending">descending</label>
      <label index="flexforms_general.detailPage">Detail Page</label>
      <label index="flexforms_general.listPage">List Page</label>
      <label index="flexforms_general.maxHighlighted">Highlights count</label>
      <label index="flexforms_general.maxItems">Items count (max)</label>
      <label index="flexforms_general.mode">What to display</label>
      <label index="flexforms_general.mode.event_calendar">Calendar</label>
      <label index="flexforms_general.mode.personListShow">List/Detail</label>
      <label index="flexforms_general.mode.personShow">Detail</label>
      <label index="flexforms_general.pages">Pages</label>
      <label index="flexforms_general.categories">Categories</label>
      <label index="flexforms_general.order">sort by</label>
      <label index="flexforms_general.start">Start</label>
      <label index="flexforms_general.lastNameAsc">Last Name (ascending)</label>
      <label index="flexforms_general.title">Title</label>
      <label index="flexforms_tab.settings">Settings</label>
      <label index="plugin.persons.title">Persons</label>
      <label index="plugin.persons.description">Displays persons.</label>
      </languageKey>
    <languageKey index="af"/>
    <languageKey index="ar"/>
    <languageKey index="bs"/>
    <languageKey index="bg"/>
    <languageKey index="ca"/>
    <languageKey index="ch"/>
    <languageKey index="cs"/>
    <languageKey index="da"/>
    <languageKey index="de" type="array">
    </languageKey>
    <languageKey index="el"/>
    <languageKey index="eo"/>
    <languageKey index="es"/>
    <languageKey index="et"/>
    <languageKey index="eu"/>
    <languageKey index="fa"/>
    <languageKey index="fi"/>
    <languageKey index="fo"/>
    <languageKey index="fr"/>
    <languageKey index="fr_CA"/>
    <languageKey index="gl"/>
    <languageKey index="he"/>
    <languageKey index="hi"/>
    <languageKey index="hr"/>
    <languageKey index="hu"/>
    <languageKey index="is"/>
    <languageKey index="it"/>
    <languageKey index="ja"/>
    <languageKey index="ka"/>
    <languageKey index="kl"/>
    <languageKey index="km"/>
    <languageKey index="ko"/>
    <languageKey index="lt"/>
    <languageKey index="lv"/>
    <languageKey index="ms"/>
    <languageKey index="nl"/>
    <languageKey index="no"/>
    <languageKey index="pl"/>
    <languageKey index="pt"/>
    <languageKey index="pt_BR"/>
    <languageKey index="ro"/>
    <languageKey index="ru"/>
    <languageKey index="sk"/>
    <languageKey index="sl"/>
    <languageKey index="sq"/>
    <languageKey index="sr"/>
    <languageKey index="sv"/>
    <languageKey index="th"/>
    <languageKey index="tr"/>
    <languageKey index="uk"/>
    <languageKey index="vi"/>
    <languageKey index="zh"/>
  </data>
</T3locallang>
